DoorLockController/__init__.py
DoorLockController/__main__.py
DoorLockController/mcp_tools.py
DoorLockController/mqtt_client.py
JC_packet/JC_packet.py
JC_packet/JC_packet_action.py
JC_packet/__init__.py
open_door_mcp-0.1.15.dist-info/METADATA
open_door_mcp-0.1.15.dist-info/WHEEL
open_door_mcp-0.1.15.dist-info/entry_points.txt
open_door_mcp-0.1.15.dist-info/top_level.txt
open_door_mcp-0.1.15.dist-info/RECORD
