Metadata-Version: 2.4
Name: open-door-mcp
Version: 0.1.15
Summary: MCP service for controlling a door lock via MQTT broker (EMQX).
Requires-Python: >=3.9
Requires-Dist: paho-mqtt>=2.1.0
Requires-Dist: fastmcp>=0.4.0
Requires-Dist: pycryptodome>=2.23.0
